jubilant/__init__.py
jubilant/_all_any.py
jubilant/_juju.py
jubilant/_pretty.py
jubilant/_task.py
jubilant/_test_helpers.py
jubilant/_version.py
jubilant/_yaml.py
jubilant/modeltypes.py
jubilant/py.typed
jubilant/secrettypes.py
jubilant/statustypes.py
jubilant-1.6.2.dist-info/METADATA
jubilant-1.6.2.dist-info/WHEEL
jubilant-1.6.2.dist-info/top_level.txt
jubilant-1.6.2.dist-info/RECORD
