Metadata-Version: 2.4
Name: jubilant
Version: 1.6.2
Summary: Juju CLI wrapper, primarily for charm integration testing
Author: The Charm Tech team at Canonical Ltd.
Project-URL: Homepage, https://github.com/canonical/jubilant
Project-URL: Repository, https://github.com/canonical/jubilant
Project-URL: Issues, https://github.com/canonical/jubilant/issues
Project-URL: Documentation, https://documentation.ubuntu.com/jubilant/
Classifier: Programming Language :: Python :: 3
Classifier: License :: OSI Approved :: Apache Software License
Classifier: Development Status :: 5 - Production/Stable
Classifier: Intended Audience :: Developers
Classifier: Intended Audience :: System Administrators
Classifier: Operating System :: MacOS :: MacOS X
Classifier: Operating System :: POSIX :: Linux
Requires-Python: >=3.8
Requires-Dist: PyYAML==6.*
